ema/__init__.py
ema/cin.py
ema/coupled.py
ema/emc.py
ema/emin.py
ema/endpoint_probes.py
ema/file.py
ema/inp.py
ema/midpoint_probes.py
ema/results.py
ema/signal.py
ema/Veelo/__init__.py
ema/Veelo/modify_current.py
ema/Veelo/preprocess.py
ema/Veelo/util.py
ema/testing/__init__.py
ema/testing/execution_test.py
ema/testing/metrics.py
ema/testing/parallelization_test.py
ema/testing/regression_test.py
ema/testing/test.py
ema/testing/validation_test.py
EMAtools-0.5.0.dist-info/LICENSE.txt
EMAtools-0.5.0.dist-info/METADATA
EMAtools-0.5.0.dist-info/WHEEL
EMAtools-0.5.0.dist-info/top_level.txt
EMAtools-0.5.0.dist-info/RECORD
