Metadata-Version: 2.1
Name: EMAtools
Version: 0.5.0
Summary: Python library for users of EMC Plus and Charge Plus.
Home-page: https://github.com/GriffinKowash/EMAtools
Author: Griffin Kowash
Author-email: griffin.kowash@ema3d.com
Project-URL: Usage guide, https://github.com/GriffinKowash/EMAtools/blob/main/README.md
Project-URL: GitHub, https://github.com/GriffinKowash/EMAtools
Project-URL: Changelog, https://github.com/GriffinKowash/EMAtools/blob/main/CHANGELOG.md
Requires-Python: >=3.7, <4
License-File: LICENSE.txt
Requires-Dist: numpy
Requires-Dist: scipy
